dkey/__init__.py
dkey/_dkey.py
dkey-0.2.3.dist-info/AUTHORS
dkey-0.2.3.dist-info/LICENSE
dkey-0.2.3.dist-info/METADATA
dkey-0.2.3.dist-info/WHEEL
dkey-0.2.3.dist-info/pbr.json
dkey-0.2.3.dist-info/top_level.txt
dkey-0.2.3.dist-info/RECORD
