Metadata-Version: 2.1
Name: dkey
Version: 0.2.3
Summary: Package to deprecate dict keys
Home-page: https://github.com/NOhs/dkey
Author: NOhs
Author-email: UNKNOWN
License: MIT
Keywords: dict,deprecation
Platform: UNKNOWN
Classifier: Programming Language :: Python
Requires-Dist: pbr
